README.md
setup.py
colorizer/__init__.py
deepaicolorizer.egg-info/PKG-INFO
deepaicolorizer.egg-info/SOURCES.txt
deepaicolorizer.egg-info/dependency_links.txt
deepaicolorizer.egg-info/not-zip-safe
deepaicolorizer.egg-info/top_level.txt