Metadata-Version: 2.1
Name: deepaicolorizer
Version: 0.0.1
Summary: Colorizer your bw photos
Home-page: UNKNOWN
Author: Islomferg
Author-email: usfvouhd@gmail.com
License: UNKNOWN
Platform: UNKNOWN
Classifier: Programming Language :: Python :: 3
Classifier: License :: OSI Approved :: MIT License
Classifier: Operating System :: OS Independent
Requires-Python: >=3.8
